list_cmath/__init__.py
list_cmath/mandelbrot.py
list_cmath-0.2.dist-info/LICENSE.txt
list_cmath-0.2.dist-info/METADATA
list_cmath-0.2.dist-info/WHEEL
list_cmath-0.2.dist-info/top_level.txt
list_cmath-0.2.dist-info/RECORD
