Metadata-Version: 2.1
Name: list_cmath
Version: 0.2
Summary: Using list to save complex.
Home-page: https://github.com/JunzePeng/list_cmath
Author: JunzePeng
Author-email: gxp@bupt.edu.cn
License: MIT
Classifier: License :: OSI Approved :: MIT License
Classifier: Programming Language :: Python :: 3
Classifier: Operating System :: OS Independent
License-File: LICENSE.txt
